README.md
setup.py
bomojo/__init__.py
bomojo/admin.py
bomojo/backends.py
bomojo/defaults.py
bomojo/middleware.py
bomojo/urls.py
bomojo/utils.py
bomojo.egg-info/PKG-INFO
bomojo.egg-info/SOURCES.txt
bomojo.egg-info/dependency_links.txt
bomojo.egg-info/requires.txt
bomojo.egg-info/top_level.txt
bomojo/matchups/__init__.py
bomojo/matchups/apps.py
bomojo/matchups/forms.py
bomojo/matchups/models.py
bomojo/matchups/renderers.py
bomojo/matchups/urls.py
bomojo/matchups/views.py
bomojo/matchups/migrations/0001_initial.py
bomojo/matchups/migrations/0002_add_defaults_to_blank_fields.py
bomojo/matchups/migrations/0003_matchup_featured.py
bomojo/matchups/migrations/0004_matchup_period_validator.py
bomojo/matchups/migrations/0005_matchup_remove_email_add_user.py
bomojo/matchups/migrations/0006_matchup_updated_on.py
bomojo/matchups/migrations/0007_matchup_datetime_indexes.py
bomojo/matchups/migrations/0008_matchup_image.py
bomojo/matchups/migrations/__init__.py
bomojo/matchups/tests/__init__.py
bomojo/matchups/tests/test_forms.py
bomojo/matchups/tests/test_models.py
bomojo/matchups/tests/test_utils.py
bomojo/matchups/tests/test_views.py
bomojo/movies/__init__.py
bomojo/movies/apps.py
bomojo/movies/models.py
bomojo/movies/renderers.py
bomojo/movies/urls.py
bomojo/movies/views.py
bomojo/movies/management/__init__.py
bomojo/movies/management/commands/__init__.py
bomojo/movies/management/commands/backfill_external_ids.py
bomojo/movies/management/commands/load_price_index_data.py
bomojo/movies/migrations/0001_initial.py
bomojo/movies/migrations/0002_movie_title_not_unique.py
bomojo/movies/migrations/0003_priceindex.py
bomojo/movies/migrations/0004_rename_external_id_legacy_id.py
bomojo/movies/migrations/0005_movie_external_id.py
bomojo/movies/migrations/__init__.py
bomojo/movies/tests/__init__.py
bomojo/movies/tests/test_models.py
bomojo/movies/tests/test_views.py
bomojo/tests/__init__.py
bomojo/tests/backends.py
bomojo/tests/settings.py
bomojo/tests/testcases.py