Metadata-Version: 2.1
Name: bomojo
Version: 0.9.3
Summary: Django app for getting movie box office data
Home-page: https://bitbucket.org/teamdtao/pybomojo
Author: Dan Tao
Author-email: daniel.tao@gmail.com
License: UNKNOWN
Platform: UNKNOWN
Requires-Python: >=3.6
Provides-Extra: test
